[
  {
    "post": "_posts/2020-10-05-radioshow.md",
    "identifier": null,
    "success": false,
    "reason": "no-identifier",
    "updates": null
  },
  {
    "post": "_posts/2020-10-18-radioshow.md",
    "identifier": null,
    "success": false,
    "reason": "no-identifier",
    "updates": null
  },
  {
    "post": "_posts/2020-11-02-radioshow.md",
    "identifier": null,
    "success": false,
    "reason": "no-identifier",
    "updates": null
  },
  {
    "post": "_posts/2020-11-16-radioshow.md",
    "identifier": null,
    "success": false,
    "reason": "no-identifier",
    "updates": null
  },
  {
    "post": "_posts/2020-12-14-radioshow.md",
    "identifier": null,
    "success": false,
    "reason": "no-identifier",
    "updates": null
  },
  {
    "post": "_posts/2020-12-29-radioshow.md",
    "identifier": null,
    "success": false,
    "reason": "no-identifier",
    "updates": null
  },
  {
    "post": "_posts/2021-01-24-radioshow.md",
    "identifier": null,
    "success": false,
    "reason": "no-identifier",
    "updates": null
  },
  {
    "post": "_posts/2021-02-12-radioshow.md",
    "identifier": null,
    "success": false,
    "reason": "no-identifier",
    "updates": null
  },
  {
    "post": "_posts/2021-02-26-radioshow.md",
    "identifier": null,
    "success": false,
    "reason": "no-identifier",
    "updates": null
  },
  {
    "post": "_posts/2021-03-07-radioshow.md",
    "identifier": null,
    "success": false,
    "reason": "no-identifier",
    "updates": null
  },
  {
    "post": "_posts/2021-03-26-radioshow.md",
    "identifier": null,
    "success": false,
    "reason": "no-identifier",
    "updates": null
  },
  {
    "post": "_posts/2021-04-14-radioshow.md",
    "identifier": null,
    "success": false,
    "reason": "no-identifier",
    "updates": null
  },
  {
    "post": "_posts/2021-05-20-radioshow.md",
    "identifier": null,
    "success": false,
    "reason": "no-identifier",
    "updates": null
  },
  {
    "post": "_posts/2021-05-27-radioshow.md",
    "identifier": null,
    "success": false,
    "reason": "no-identifier",
    "updates": null
  },
  {
    "post": "_posts/2021-06-11-radioshow.md",
    "identifier": null,
    "success": false,
    "reason": "no-identifier",
    "updates": null
  },
  {
    "post": "_posts/2021-06-20-radioshow.md",
    "identifier": null,
    "success": false,
    "reason": "no-identifier",
    "updates": null
  },
  {
    "post": "_posts/2021-07-04-radioshow.md",
    "identifier": null,
    "success": false,
    "reason": "no-identifier",
    "updates": null
  },
  {
    "post": "_posts/2021-07-23-radioshow.md",
    "identifier": null,
    "success": false,
    "reason": "no-identifier",
    "updates": null
  },
  {
    "post": "_posts/2021-08-18-radioshow.md",
    "identifier": null,
    "success": false,
    "reason": "no-identifier",
    "updates": null
  },
  {
    "post": "_posts/2021-08-31-radioshow.md",
    "identifier": null,
    "success": false,
    "reason": "no-identifier",
    "updates": null
  },
  {
    "post": "_posts/2021-09-12-radioshow.md",
    "identifier": null,
    "success": false,
    "reason": "no-identifier",
    "updates": null
  },
  {
    "post": "_posts/2021-09-26-radioshow.md",
    "identifier": null,
    "success": false,
    "reason": "no-identifier",
    "updates": null
  },
  {
    "post": "_posts/2021-10-27-radioshow.md",
    "identifier": null,
    "success": false,
    "reason": "no-identifier",
    "updates": null
  },
  {
    "post": "_posts/2021-11-07-radioshow.md",
    "identifier": null,
    "success": false,
    "reason": "no-identifier",
    "updates": null
  },
  {
    "post": "_posts/2021-11-22-radioshow.md",
    "identifier": null,
    "success": false,
    "reason": "no-identifier",
    "updates": null
  },
  {
    "post": "_posts/2021-12-19-radioshow.md",
    "identifier": null,
    "success": false,
    "reason": "no-identifier",
    "updates": null
  },
  {
    "post": "_posts/2022-01-02-radioshow.md",
    "identifier": null,
    "success": false,
    "reason": "no-identifier",
    "updates": null
  },
  {
    "post": "_posts/2022-01-21-radioshow.md",
    "identifier": null,
    "success": false,
    "reason": "no-identifier",
    "updates": null
  },
  {
    "post": "_posts/2022-02-07-radioshow.md",
    "identifier": null,
    "success": false,
    "reason": "no-identifier",
    "updates": null
  },
  {
    "post": "_posts/2022-02-13-radioshow.md",
    "identifier": null,
    "success": false,
    "reason": "no-identifier",
    "updates": null
  },
  {
    "post": "_posts/2022-03-03-radioshow.md",
    "identifier": null,
    "success": false,
    "reason": "no-identifier",
    "updates": null
  },
  {
    "post": "_posts/2022-03-18-radioshow.md",
    "identifier": null,
    "success": false,
    "reason": "no-identifier",
    "updates": null
  },
  {
    "post": "_posts/2022-04-14-radioshow.md",
    "identifier": null,
    "success": false,
    "reason": "no-identifier",
    "updates": null
  },
  {
    "post": "_posts/2022-04-27-radioshow.md",
    "identifier": null,
    "success": false,
    "reason": "no-identifier",
    "updates": null
  },
  {
    "post": "_posts/2022-05-18-radioshow.md",
    "identifier": null,
    "success": false,
    "reason": "no-identifier",
    "updates": null
  },
  {
    "post": "_posts/2022-06-24-radioshow.md",
    "identifier": null,
    "success": false,
    "reason": "no-identifier",
    "updates": null
  },
  {
    "post": "_posts/2022-07-20-radioshow.md",
    "identifier": null,
    "success": false,
    "reason": "no-identifier",
    "updates": null
  },
  {
    "post": "_posts/2022-09-14-radioshow.md",
    "identifier": null,
    "success": false,
    "reason": "no-identifier",
    "updates": null
  },
  {
    "post": "_posts/2022-09-27-radioshow.md",
    "identifier": null,
    "success": false,
    "reason": "no-identifier",
    "updates": null
  },
  {
    "post": "_posts/2022-10-27-radioshow.md",
    "identifier": null,
    "success": false,
    "reason": "no-identifier",
    "updates": null
  },
  {
    "post": "_posts/2022-11-15-radioshow.md",
    "identifier": null,
    "success": false,
    "reason": "no-identifier",
    "updates": null
  },
  {
    "post": "_posts/2022-11-29-radioshow.md",
    "identifier": null,
    "success": false,
    "reason": "no-identifier",
    "updates": null
  },
  {
    "post": "_posts/2022-12-27-radioshow.md",
    "identifier": "2022-12-25-nogallnoglory",
    "success": true,
    "reason": null,
    "updates": {
      "audio_url": "https://archive.org/download/2022-12-25-nogallnoglory/2022-12-25-NOGALLNOGLORY-JIM.mp3",
      "audio_length": "283252096",
      "audio_mime": "audio/mpeg",
      "itunes_duration": "01:58:01"
    }
  },
  {
    "post": "_posts/2023-01-09-radioshow.md",
    "identifier": "2023-01-07-nogallnoglory",
    "success": true,
    "reason": null,
    "updates": {
      "audio_url": "https://archive.org/download/2023-01-07-nogallnoglory/2023-01-07-NOGALLNOGLORY.mp3",
      "audio_length": "366954690",
      "audio_mime": "audio/mpeg",
      "itunes_duration": "02:32:53"
    }
  },
  {
    "post": "_posts/2023-01-25-radioshow.md",
    "identifier": "2023-01-22-nogallnoglory",
    "success": true,
    "reason": null,
    "updates": {
      "audio_url": "https://archive.org/download/2023-01-22-nogallnoglory/2023-01-22-NOGALLNOGLORY.mp3",
      "audio_length": "285011698",
      "audio_mime": "audio/mpeg",
      "itunes_duration": "01:58:45"
    }
  },
  {
    "post": "_posts/2023-02-09-radioshow.md",
    "identifier": "2022-02-05-nogallnoglory",
    "success": true,
    "reason": null,
    "updates": {
      "audio_url": "https://archive.org/download/2022-02-05-nogallnoglory/2022-02-05-NOGALLNOGLORY-JIM.mp3",
      "audio_length": "288924851",
      "audio_mime": "audio/mpeg",
      "itunes_duration": "02:00:23"
    }
  },
  {
    "post": "_posts/2023-03-22-radioshow.md",
    "identifier": "2022-03-19-nogallnoglory",
    "success": true,
    "reason": null,
    "updates": {
      "audio_url": "https://archive.org/download/2022-03-19-nogallnoglory/2022-03-19-NOGALLNOGLORY.mp3",
      "audio_length": "278982652",
      "audio_mime": "audio/mpeg",
      "itunes_duration": "01:56:14"
    }
  },
  {
    "post": "_posts/2023-07-10-radioshow.md",
    "identifier": "2023-07-09-nogallnoglory",
    "success": true,
    "reason": null,
    "updates": {
      "audio_url": "https://archive.org/download/2023-07-09-nogallnoglory/2023-07-09-NOGALLNOGLORY-JIM.mp3",
      "audio_length": "292050142",
      "audio_mime": "audio/mpeg",
      "itunes_duration": "02:01:41"
    }
  },
  {
    "post": "_posts/2023-08-07-radioshow.md",
    "identifier": "2023-08-6-nogallnoglory",
    "success": true,
    "reason": null,
    "updates": {
      "audio_url": "https://archive.org/download/2023-08-6-nogallnoglory/2023-08--6-NOGALLNOGLORY-JIM.mp3",
      "audio_length": "279777779",
      "audio_mime": "audio/mpeg",
      "itunes_duration": "01:56:34"
    }
  },
  {
    "post": "_posts/2023-08-20-radioshow.md",
    "identifier": "2023-08-20-nogall-noglory",
    "success": true,
    "reason": null,
    "updates": {
      "audio_url": "https://archive.org/download/2023-08-20-nogall-noglory/2023-08-20-NOGALL-NOGLORY-jim.mp3",
      "audio_length": "289358494",
      "audio_mime": "audio/mpeg",
      "itunes_duration": "02:00:33"
    }
  },
  {
    "post": "_posts/2023-09-19-radioshow.md",
    "identifier": "2023-09-17-nogallnoglory_20230919",
    "success": true,
    "reason": null,
    "updates": {
      "audio_url": "https://archive.org/download/2023-09-17-nogallnoglory_20230919/2023-09-17-NOGALLNOGLORY.mp3",
      "audio_length": "279200995",
      "audio_mime": "audio/mpeg",
      "itunes_duration": "01:56:20"
    }
  },
  {
    "post": "_posts/2023-10-11-radioshow.md",
    "identifier": "2023-10-01-nogallnoglory",
    "success": true,
    "reason": null,
    "updates": {
      "audio_url": "https://archive.org/download/2023-10-01-nogallnoglory/2023-10-01-NOGALLNOGLORY-jim.mp3",
      "audio_length": "280172857",
      "audio_mime": "audio/mpeg",
      "itunes_duration": "01:56:44"
    }
  },
  {
    "post": "_posts/2023-10-24-radioshow.md",
    "identifier": "2023-10-01-nogallnoglory",
    "success": true,
    "reason": null,
    "updates": {
      "audio_url": "https://archive.org/download/2023-10-01-nogallnoglory/2023-10-01-NOGALLNOGLORY-jim.mp3",
      "audio_length": "280172857",
      "audio_mime": "audio/mpeg",
      "itunes_duration": "01:56:44"
    }
  },
  {
    "post": "_posts/2023-12-10-radioshow.md",
    "identifier": "2023-12-10-nogallnoglory",
    "success": true,
    "reason": null,
    "updates": {
      "audio_url": "https://archive.org/download/2023-12-10-nogallnoglory/2023-12-10-NOGALLNOGLORY-JIM.mp3",
      "audio_length": "285639753",
      "audio_mime": "audio/mpeg",
      "itunes_duration": "01:59:00"
    }
  },
  {
    "post": "_posts/2023-12-24-radioshow.md",
    "identifier": "2023-12-24-nogallnoglory",
    "success": true,
    "reason": null,
    "updates": {
      "audio_url": "https://archive.org/download/2023-12-24-nogallnoglory/2023-12-24-NOGALLNOGLORY-JIM.mp3",
      "audio_length": "279897009",
      "audio_mime": "audio/mpeg",
      "itunes_duration": "01:56:37"
    }
  },
  {
    "post": "_posts/2024-01-10-radioshow.md",
    "identifier": "2024-01-07-nogallnoglory",
    "success": true,
    "reason": null,
    "updates": {
      "audio_url": "https://archive.org/download/2024-01-07-nogallnoglory/2024-01-07-NOGALLNOGLORY-JIM.mp3",
      "audio_length": "275773756",
      "audio_mime": "audio/mpeg",
      "itunes_duration": "01:54:54"
    }
  },
  {
    "post": "_posts/2024-01-21-radioshow.md",
    "identifier": "2024-01-21-nogallnoglory",
    "success": true,
    "reason": null,
    "updates": {
      "audio_url": "https://archive.org/download/2024-01-21-nogallnoglory/2024-01-21-NOGALLNOGLORY-JIM.mp3",
      "audio_length": "272837624",
      "audio_mime": "audio/mpeg",
      "itunes_duration": "01:53:40"
    }
  },
  {
    "post": "_posts/2024-02-04-radioshow.md",
    "identifier": "2024-02-04-nogallnoglory",
    "success": true,
    "reason": null,
    "updates": {
      "audio_url": "https://archive.org/download/2024-02-04-nogallnoglory/2024-02-04-NOGALLNOGLORY-JIM.mp3",
      "audio_length": "285860138",
      "audio_mime": "audio/mpeg",
      "itunes_duration": "01:59:06"
    }
  },
  {
    "post": "_posts/2024-03-03-radioshow.md",
    "identifier": "2024-03-03-nogallnoglory",
    "success": true,
    "reason": null,
    "updates": {
      "audio_url": "https://archive.org/download/2024-03-03-nogallnoglory/2024-03-03-NOGALLNOGLORY-JIM.mp3",
      "audio_length": "273688139",
      "audio_mime": "audio/mpeg",
      "itunes_duration": "01:54:02"
    }
  },
  {
    "post": "_posts/2024-03-17-radioshow.md",
    "identifier": "2024-03-17-nogallnoglory",
    "success": true,
    "reason": null,
    "updates": {
      "audio_url": "https://archive.org/download/2024-03-17-nogallnoglory/2024-03-17-NOGALLNOGLORY-JIM.mp3",
      "audio_length": "272146987",
      "audio_mime": "audio/mpeg",
      "itunes_duration": "01:53:23"
    }
  },
  {
    "post": "_posts/2024-04-14-radioshow.md",
    "identifier": "2024-04-14-nogallnoglory",
    "success": true,
    "reason": null,
    "updates": {
      "audio_url": "https://archive.org/download/2024-04-14-nogallnoglory/2024-04-14-NOGALLNOGLORY-JIM.mp3",
      "audio_length": "279429862",
      "audio_mime": "audio/mpeg",
      "itunes_duration": "01:56:25"
    }
  },
  {
    "post": "_posts/2024-05-26-radioshow.md",
    "identifier": "2021-05-26-nogallnoglory",
    "success": true,
    "reason": null,
    "updates": {
      "audio_url": "https://archive.org/download/2021-05-26-nogallnoglory/2021-05-26-nogallnoglory-jim.mp3",
      "audio_length": "282957575",
      "audio_mime": "audio/mpeg",
      "itunes_duration": "01:57:53"
    }
  },
  {
    "post": "_posts/2024-06-09-radioshow.md",
    "identifier": "2021-06-10-nogallnoglory",
    "success": true,
    "reason": null,
    "updates": {
      "audio_url": "https://archive.org/download/2021-06-10-nogallnoglory/2021-06-10-nogallnoglory-jim.mp3",
      "audio_length": "276141706",
      "audio_mime": "audio/mpeg",
      "itunes_duration": "01:55:03"
    }
  },
  {
    "post": "_posts/2024-06-23-radioshow.md",
    "identifier": "2024-06-23-nogallnoglory",
    "success": true,
    "reason": null,
    "updates": {
      "audio_url": "https://archive.org/download/2024-06-23-nogallnoglory/2021-06-23-nogallnoglory-jim.mp3",
      "audio_length": "279368123",
      "audio_mime": "audio/mpeg",
      "itunes_duration": "01:56:24"
    }
  },
  {
    "post": "_posts/2024-07-07-radioshow.md",
    "identifier": "2023-07-07-nogallnoglory",
    "success": true,
    "reason": null,
    "updates": {
      "audio_url": "https://archive.org/download/2023-07-07-nogallnoglory/2023-07-07-nogallnoglory-jim.mp3",
      "audio_length": "286890296",
      "audio_mime": "audio/mpeg",
      "itunes_duration": "01:59:32"
    }
  },
  {
    "post": "_posts/2024-08-09-radioshow.md",
    "identifier": "2024-08-03-nogallnoglory",
    "success": true,
    "reason": null,
    "updates": {
      "audio_url": "https://archive.org/download/2024-08-03-nogallnoglory/2024-08-03-nogallnoglory-jim.mp3",
      "audio_length": "283565478",
      "audio_mime": "audio/mpeg",
      "itunes_duration": "01:58:09"
    }
  },
  {
    "post": "_posts/2024-08-25-radioshow.md",
    "identifier": "2024-08-25-nogallnoglory",
    "success": true,
    "reason": null,
    "updates": {
      "audio_url": "https://archive.org/download/2024-08-25-nogallnoglory/2024-08-25-nogallnoglory-jim.mp3",
      "audio_length": "276407165",
      "audio_mime": "audio/mpeg",
      "itunes_duration": "01:55:10"
    }
  },
  {
    "post": "_posts/2024-09-08-radioshow.md",
    "identifier": "2024-09-08-nogallnoglory",
    "success": true,
    "reason": null,
    "updates": {
      "audio_url": "https://archive.org/download/2024-09-08-nogallnoglory/2024-09-08-nogallnoglory-jim.mp3",
      "audio_length": "287570704",
      "audio_mime": "audio/mpeg",
      "itunes_duration": "01:59:49"
    }
  },
  {
    "post": "_posts/2024-09-22-radioshow.md",
    "identifier": "2024-09-22-nogallnoglory",
    "success": true,
    "reason": null,
    "updates": {
      "audio_url": "https://archive.org/download/2024-09-22-nogallnoglory/2024-09-22-nogallnoglory-jim.mp3",
      "audio_length": "271915338",
      "audio_mime": "audio/mpeg",
      "itunes_duration": "01:53:17"
    }
  },
  {
    "post": "_posts/2024-10-06-radioshow.md",
    "identifier": "2024-10-06-nogallnoglory",
    "success": true,
    "reason": null,
    "updates": {
      "audio_url": "https://archive.org/download/2024-10-06-nogallnoglory/2024-10-06-nogallnoglory-jim.mp3",
      "audio_length": "255847623",
      "audio_mime": "audio/mpeg",
      "itunes_duration": "01:46:36"
    }
  },
  {
    "post": "_posts/2024-11-10-radioshow.md",
    "identifier": "2024-11-10-nogallnoglory",
    "success": true,
    "reason": null,
    "updates": {
      "audio_url": "https://archive.org/download/2024-11-10-nogallnoglory/2024-11-10-nogallnoglory-jim.mp3",
      "audio_length": "282257348",
      "audio_mime": "audio/mpeg",
      "itunes_duration": "01:57:36"
    }
  },
  {
    "post": "_posts/2024-12-21-radioshow.md",
    "identifier": "2024-12-15-nogallnoglory",
    "success": true,
    "reason": null,
    "updates": {
      "audio_url": "https://archive.org/download/2024-12-15-nogallnoglory/2024-12-15-nogallnoglory-jim.mp3",
      "audio_length": "279620252",
      "audio_mime": "audio/mpeg",
      "itunes_duration": "01:56:30"
    }
  },
  {
    "post": "_posts/2024-12-31-radioshow.md",
    "identifier": "2025-01-12-nogallnoglory",
    "success": true,
    "reason": null,
    "updates": {
      "audio_url": "https://archive.org/download/2025-01-12-nogallnoglory/2025-01-12-nogallnoglory-jim.mp3",
      "audio_length": "283813532",
      "audio_mime": "audio/mpeg",
      "itunes_duration": "01:58:15"
    }
  },
  {
    "post": "_posts/2025-01-26-radioshow.md",
    "identifier": "2025-01-26-nogallnoglory",
    "success": true,
    "reason": null,
    "updates": {
      "audio_url": "https://archive.org/download/2025-01-26-nogallnoglory/2025-01-26-nogallnoglory-jim.mp3",
      "audio_length": "286178864",
      "audio_mime": "audio/mpeg",
      "itunes_duration": "01:59:14"
    }
  },
  {
    "post": "_posts/2025-02-09-radioshow.md",
    "identifier": "2025-02-09-nogallnoglory",
    "success": true,
    "reason": null,
    "updates": {
      "audio_url": "https://archive.org/download/2025-02-09-nogallnoglory/2025-02-09-nogallnoglory-jim.mp3",
      "audio_length": "278572893",
      "audio_mime": "audio/mpeg",
      "itunes_duration": "01:56:04"
    }
  },
  {
    "post": "_posts/2025-03-09-radioshow.md",
    "identifier": "2025-03-09-nogallnoglory",
    "success": true,
    "reason": null,
    "updates": {
      "audio_url": "https://archive.org/download/2025-03-09-nogallnoglory/2025-03-09-nogallnoglory-jim.mp3",
      "audio_length": "279139356",
      "audio_mime": "audio/mpeg",
      "itunes_duration": "01:56:18"
    }
  },
  {
    "post": "_posts/2025-03-30-radioshow.md",
    "identifier": "2025-03-30-nogallnoglory",
    "success": true,
    "reason": null,
    "updates": {
      "audio_url": "https://archive.org/download/2025-03-30-nogallnoglory/2025-03-30-nogallnoglory-jim.mp3",
      "audio_length": "280526536",
      "audio_mime": "audio/mpeg",
      "itunes_duration": "01:56:53"
    }
  },
  {
    "post": "_posts/2025-04-13-radioshow.md",
    "identifier": "2025-04-13-nogallnoglory",
    "success": true,
    "reason": null,
    "updates": {
      "audio_url": "https://archive.org/download/2025-04-13-nogallnoglory/2025-04-13-nogallnoglory-jim.mp3",
      "audio_length": "264246812",
      "audio_mime": "audio/mpeg",
      "itunes_duration": "01:50:06"
    }
  },
  {
    "post": "_posts/2025-05-11-radioshow.md",
    "identifier": "2025-05-11-nogallnoglory",
    "success": true,
    "reason": null,
    "updates": {
      "audio_url": "https://archive.org/download/2025-05-11-nogallnoglory/2025-05-11-nogallnoglory-jim.mp3",
      "audio_length": "290100336",
      "audio_mime": "audio/mpeg",
      "itunes_duration": "02:00:52"
    }
  },
  {
    "post": "_posts/2025-05-25-radioshow.md",
    "identifier": "2025-05-25-nogallnoglory",
    "success": true,
    "reason": null,
    "updates": {
      "audio_url": "https://archive.org/download/2025-05-25-nogallnoglory/2025-05-25-nogallnoglory-jim.mp3",
      "audio_length": "288566441",
      "audio_mime": "audio/mpeg",
      "itunes_duration": "02:00:14"
    }
  },
  {
    "post": "_posts/2025-06-22-radioshow.md",
    "identifier": "2025-06-22-nogallnoglory",
    "success": true,
    "reason": null,
    "updates": {
      "audio_url": "https://archive.org/download/2025-06-22-nogallnoglory/2025-06-22-nogallnoglory-jim.mp3",
      "audio_length": "286188254",
      "audio_mime": "audio/mpeg",
      "itunes_duration": "01:59:14"
    }
  },
  {
    "post": "_posts/2025-07-06-radioshow.md",
    "identifier": "2025-07-06-nogallnoglory",
    "success": true,
    "reason": null,
    "updates": {
      "audio_url": "https://archive.org/download/2025-07-06-nogallnoglory/2025-07-06-nogallnoglory-jim.mp3",
      "audio_length": "274638022",
      "audio_mime": "audio/mpeg",
      "itunes_duration": "01:54:25"
    }
  },
  {
    "post": "_posts/2025-07-20-radioshow.md",
    "identifier": "2025-07-20-nogallnoglory",
    "success": true,
    "reason": null,
    "updates": {
      "audio_url": "https://archive.org/download/2025-07-20-nogallnoglory/2025-07-20-nogallnoglory-jim.mp3",
      "audio_length": "268406492",
      "audio_mime": "audio/mpeg",
      "itunes_duration": "01:51:50"
    }
  },
  {
    "post": "_posts/2025-08-02-radioshow.md",
    "identifier": "2025-08-02-nogallnoglory",
    "success": true,
    "reason": null,
    "updates": {
      "audio_url": "https://archive.org/download/2025-08-02-nogallnoglory/2025-08-02-nogallnoglory-jim.mp3",
      "audio_length": "257437548",
      "audio_mime": "audio/mpeg",
      "itunes_duration": "01:47:15"
    }
  },
  {
    "post": "_posts/2025-08-30-radioshow.md",
    "identifier": "2025-08-30-nogallnoglory",
    "success": true,
    "reason": null,
    "updates": {
      "audio_url": "https://archive.org/download/2025-08-30-nogallnoglory/2025-08-30-NOGALLNOGLORY-jim.mp3",
      "audio_length": "270274652",
      "audio_mime": "audio/mpeg",
      "itunes_duration": "01:52:36"
    }
  },
  {
    "post": "_posts/2025-09-14-radioshow.md",
    "identifier": "2025-09-14-nogallnoglory",
    "success": true,
    "reason": null,
    "updates": {
      "audio_url": "https://archive.org/download/2025-09-14-nogallnoglory/2025-09-14-NOGALLNOGLORY-jim.mp3",
      "audio_length": "275560412",
      "audio_mime": "audio/mpeg",
      "itunes_duration": "01:54:48"
    }
  },
  {
    "post": "_posts/2025-10-05-radioshow.md",
    "identifier": "2025-10-05-nogallnoglory",
    "success": true,
    "reason": null,
    "updates": {
      "audio_url": "https://archive.org/download/2025-10-05-nogallnoglory/2025-10-05-NOGALLNOGLORY-jim.mp3",
      "audio_length": "279960092",
      "audio_mime": "audio/mpeg",
      "itunes_duration": "01:56:38"
    }
  },
  {
    "post": "_posts/2025-10-26-radioshow.md",
    "identifier": "2025-10-26-nogallnoglory",
    "success": true,
    "reason": null,
    "updates": {
      "audio_url": "https://archive.org/download/2025-10-26-nogallnoglory/2025-10-26-NOGALLNOGLORY-jim.mp3",
      "audio_length": "278570014",
      "audio_mime": "audio/mpeg",
      "itunes_duration": "01:56:04"
    }
  },
  {
    "post": "_posts/2025-11-23-radioshow.md",
    "identifier": "2025-11-23-nogallnoglory",
    "success": true,
    "reason": null,
    "updates": {
      "audio_url": "https://archive.org/download/2025-11-23-nogallnoglory/2025-11-23-NOGALLNOGLORY-jim.mp3",
      "audio_length": "287498012",
      "audio_mime": "audio/mpeg",
      "itunes_duration": "01:59:47"
    }
  },
  {
    "post": "_posts/2025-12-07-radioshow.md",
    "identifier": "2025-12-07-nogallnoglory",
    "success": true,
    "reason": null,
    "updates": {
      "audio_url": "https://archive.org/download/2025-12-07-nogallnoglory/2025-12-07-NOGALLNOGLORY-jim.mp3",
      "audio_length": "286417156",
      "audio_mime": "audio/mpeg",
      "itunes_duration": "01:59:20"
    }
  },
  {
    "post": "_posts/2025-12-21-radioshow.md",
    "identifier": "2025-12-21-nogallnoglory",
    "success": true,
    "reason": null,
    "updates": {
      "audio_url": "https://archive.org/download/2025-12-21-nogallnoglory/2025-12-21-NOGALLNOGLORY-jim.mp3",
      "audio_length": "280816417",
      "audio_mime": "audio/mpeg",
      "itunes_duration": "01:57:00"
    }
  },
  {
    "post": "_posts/2026-01-04-radioshow.md",
    "identifier": "2026-01-04-nogallnoglory",
    "success": true,
    "reason": null,
    "updates": {
      "audio_url": "https://archive.org/download/2026-01-04-nogallnoglory/2026-01-04-NOGALLNOGLORY-jim.mp3",
      "audio_length": "315084891",
      "audio_mime": "audio/mpeg",
      "itunes_duration": "02:11:17"
    }
  },
  {
    "post": "_posts/2026-01-31-radioshow.md",
    "identifier": "2026-01-18-nogallnoglory",
    "success": true,
    "reason": null,
    "updates": {
      "audio_url": "https://archive.org/download/2026-01-18-nogallnoglory/2026-01-18-NOGALLNOGLORY-jim.mp3",
      "audio_length": "276911132",
      "audio_mime": "audio/mpeg",
      "itunes_duration": "01:55:22"
    }
  }
]